propainter/__init__.py
propainter/propainter_video.py
propainter-0.0.4.dist-info/LICENSE
propainter-0.0.4.dist-info/METADATA
propainter-0.0.4.dist-info/WHEEL
propainter-0.0.4.dist-info/top_level.txt
propainter-0.0.4.dist-info/RECORD
