Metadata-Version: 2.1
Name: propainter
Version: 0.0.4
Summary: Streaming ProPainter
Home-page: https://github.com/osmr/propainter
Author: Oleg Sémery
Author-email: osemery@gmail.com
License: MIT
Keywords: video-inpaining propainter pytorch
Classifier: Development Status :: 3 - Alpha
Classifier: Intended Audience :: Science/Research
Classifier: License :: OSI Approved :: MIT License
Classifier: Operating System :: OS Independent
Classifier: Programming Language :: Python :: 3
Classifier: Topic :: Scientific/Engineering :: Image Recognition
Requires-Python: >=3.10
License-File: LICENSE
Requires-Dist: pytorchcv
Requires-Dist: opencv-python
Requires-Dist: pillow
Requires-Dist: scipy
